arctic/__init__.py
arctic/apps.py
arctic/defaults.py
arctic/forms.py
arctic/generics.py
arctic/loading.py
arctic/mixins.py
arctic/models.py
arctic/multiform.py
arctic/paginator.py
arctic/signals.py
arctic/urls.py
arctic/utils.py
arctic/views.py
arctic/widgets.py
arctic/bin/__init__.py
arctic/bin/arctic.py
arctic/locale/__init__.py
arctic/locale/nl/__init__.py
arctic/locale/nl/LC_MESSAGES/django.mo
arctic/locale/nl/LC_MESSAGES/django.po
arctic/migrations/0001_initial.py
arctic/migrations/0002_auto_20180618_1045.py
arctic/migrations/__init__.py
arctic/project_template/app/__init__.py
arctic/project_template/app/apps.py
arctic/project_template/app/forms.py
arctic/project_template/app/models.py
arctic/project_template/app/tests.py
arctic/project_template/app/urls.py
arctic/project_template/app/views.py
arctic/project_template/start/__init__.py
arctic/project_template/start/manage.py
arctic/project_template/start/config/__init__.py
arctic/project_template/start/config/settings.py
arctic/project_template/start/config/urls.py
arctic/project_template/start/config/wsgi.py
arctic/project_template/start/dashboard/__init__.py
arctic/project_template/start/dashboard/apps.py
arctic/project_template/start/dashboard/models.py
arctic/project_template/start/dashboard/urls.py
arctic/project_template/start/dashboard/views.py
arctic/project_template/start/dashboard/migrations/__init__.py
arctic/project_template/start/dashboard/templates/dashboard.html
arctic/project_template/start/requirements/base.txt
arctic/static/arctic/dist/assets/css/arctic.css
arctic/static/arctic/dist/assets/fonts/fontawesome-webfont.eot
arctic/static/arctic/dist/assets/fonts/fontawesome-webfont.svg
arctic/static/arctic/dist/assets/fonts/fontawesome-webfont.ttf
arctic/static/arctic/dist/assets/fonts/fontawesome-webfont.woff
arctic/static/arctic/dist/assets/fonts/fontawesome-webfont.woff2
arctic/static/arctic/dist/assets/img/arctic_logo.svg
arctic/static/arctic/dist/assets/js/app.js
django_arctic-1.5.4.dist-info/LICENSE
django_arctic-1.5.4.dist-info/METADATA
django_arctic-1.5.4.dist-info/WHEEL
django_arctic-1.5.4.dist-info/entry_points.txt
django_arctic-1.5.4.dist-info/top_level.txt
django_arctic-1.5.4.dist-info/RECORD
